odoo/addons/purchase_product_warn_message/README.rst
odoo/addons/purchase_product_warn_message/__init__.py
odoo/addons/purchase_product_warn_message/__manifest__.py
odoo/addons/purchase_product_warn_message/i18n/es.po
odoo/addons/purchase_product_warn_message/models/__init__.py
odoo/addons/purchase_product_warn_message/models/purchase_order.py
odoo/addons/purchase_product_warn_message/readme/CONFIGURE.md
odoo/addons/purchase_product_warn_message/readme/CONTRIBUTORS.md
odoo/addons/purchase_product_warn_message/readme/DESCRIPTION.md
odoo/addons/purchase_product_warn_message/readme/USAGE.md
odoo/addons/purchase_product_warn_message/static/description/icon.png
odoo/addons/purchase_product_warn_message/static/description/index.html
odoo/addons/purchase_product_warn_message/views/purchase_order_views.xml
odoo_addon_purchase_product_warn_message-17.0.1.0.0.1.dist-info/METADATA
odoo_addon_purchase_product_warn_message-17.0.1.0.0.1.dist-info/WHEEL
odoo_addon_purchase_product_warn_message-17.0.1.0.0.1.dist-info/top_level.txt
odoo_addon_purchase_product_warn_message-17.0.1.0.0.1.dist-info/RECORD
